epona/__init__.py
epona/common.py
epona/settings.py
epona/auth/__init__.py
epona/auth/models.py
epona/auth/routers.py
epona/auth/schemas.py
epona/auth/services.py
epona/layers/__init__.py
epona/layers/models.py
epona/layers/routers.py
epona/layers/schemas.py
epona/layers/services.py
epona/pessoas/__init__.py
epona/pessoas/models.py
epona/pessoas/routers.py
epona/pessoas/schemas.py
epona/pessoas/services.py
epona_api_core-0.3.4.dist-info/METADATA
epona_api_core-0.3.4.dist-info/WHEEL
epona_api_core-0.3.4.dist-info/top_level.txt
epona_api_core-0.3.4.dist-info/RECORD
