Metadata-Version: 2.4
Name: epona-api-core
Version: 0.3.4
Summary: Epona API-Core
Author: Antonio Marcos
Author-email: marcos@eponaconsultoria.com.br
Classifier: Programming Language :: Python :: 3.9
Requires-Python: >=3.9.0
Requires-Dist: fastapi==0.115.12
Requires-Dist: asyncpg==0.30.0
Requires-Dist: boto3==1.28.18
Requires-Dist: jinja2==3.1.6
Requires-Dist: openpyxl==3.1.5
Requires-Dist: pydantic==2.11.4
Requires-Dist: python-multipart==0.0.20
Requires-Dist: pyjwt==2.10.1
Requires-Dist: pyshp==2.3.1
Requires-Dist: tortoise-orm==0.25.0
Requires-Dist: passlib[bcrypt]==1.7.4
Dynamic: author
Dynamic: author-email
Dynamic: classifier
Dynamic: description
Dynamic: description-content-type
Dynamic: requires-dist
Dynamic: requires-python
Dynamic: summary
